[{"name":"BACK","description":"com.wannaverse.chimesdk.CameraFacing.BACK","location":"chime-sdk/com.wannaverse.chimesdk/-camera-facing/-b-a-c-k/index.html","searchKeys":["BACK","BACK","com.wannaverse.chimesdk.CameraFacing.BACK"]},{"name":"BLUETOOTH","description":"com.wannaverse.chimesdk.AudioDeviceType.BLUETOOTH","location":"chime-sdk/com.wannaverse.chimesdk/-audio-device-type/-b-l-u-e-t-o-o-t-h/index.html","searchKeys":["BLUETOOTH","BLUETOOTH","com.wannaverse.chimesdk.AudioDeviceType.BLUETOOTH"]},{"name":"BUILT_IN_MIC","description":"com.wannaverse.chimesdk.AudioDeviceType.BUILT_IN_MIC","location":"chime-sdk/com.wannaverse.chimesdk/-audio-device-type/-b-u-i-l-t_-i-n_-m-i-c/index.html","searchKeys":["BUILT_IN_MIC","BUILT_IN_MIC","com.wannaverse.chimesdk.AudioDeviceType.BUILT_IN_MIC"]},{"name":"CONNECTED","description":"com.wannaverse.chimesdk.ConnectionStatus.CONNECTED","location":"chime-sdk/com.wannaverse.chimesdk/-connection-status/-c-o-n-n-e-c-t-e-d/index.html","searchKeys":["CONNECTED","CONNECTED","com.wannaverse.chimesdk.ConnectionStatus.CONNECTED"]},{"name":"CONNECTING","description":"com.wannaverse.chimesdk.ConnectionStatus.CONNECTING","location":"chime-sdk/com.wannaverse.chimesdk/-connection-status/-c-o-n-n-e-c-t-i-n-g/index.html","searchKeys":["CONNECTING","CONNECTING","com.wannaverse.chimesdk.ConnectionStatus.CONNECTING"]},{"name":"DISCONNECTED","description":"com.wannaverse.chimesdk.ConnectionStatus.DISCONNECTED","location":"chime-sdk/com.wannaverse.chimesdk/-connection-status/-d-i-s-c-o-n-n-e-c-t-e-d/index.html","searchKeys":["DISCONNECTED","DISCONNECTED","com.wannaverse.chimesdk.ConnectionStatus.DISCONNECTED"]},{"name":"EARPIECE","description":"com.wannaverse.chimesdk.AudioDeviceType.EARPIECE","location":"chime-sdk/com.wannaverse.chimesdk/-audio-device-type/-e-a-r-p-i-e-c-e/index.html","searchKeys":["EARPIECE","EARPIECE","com.wannaverse.chimesdk.AudioDeviceType.EARPIECE"]},{"name":"ERROR","description":"com.wannaverse.chimesdk.ConnectionStatus.ERROR","location":"chime-sdk/com.wannaverse.chimesdk/-connection-status/-e-r-r-o-r/index.html","searchKeys":["ERROR","ERROR","com.wannaverse.chimesdk.ConnectionStatus.ERROR"]},{"name":"FRONT","description":"com.wannaverse.chimesdk.CameraFacing.FRONT","location":"chime-sdk/com.wannaverse.chimesdk/-camera-facing/-f-r-o-n-t/index.html","searchKeys":["FRONT","FRONT","com.wannaverse.chimesdk.CameraFacing.FRONT"]},{"name":"POOR_CONNECTION","description":"com.wannaverse.chimesdk.ConnectionStatus.POOR_CONNECTION","location":"chime-sdk/com.wannaverse.chimesdk/-connection-status/-p-o-o-r_-c-o-n-n-e-c-t-i-o-n/index.html","searchKeys":["POOR_CONNECTION","POOR_CONNECTION","com.wannaverse.chimesdk.ConnectionStatus.POOR_CONNECTION"]},{"name":"RECONNECTING","description":"com.wannaverse.chimesdk.ConnectionStatus.RECONNECTING","location":"chime-sdk/com.wannaverse.chimesdk/-connection-status/-r-e-c-o-n-n-e-c-t-i-n-g/index.html","searchKeys":["RECONNECTING","RECONNECTING","com.wannaverse.chimesdk.ConnectionStatus.RECONNECTING"]},{"name":"SPEAKER","description":"com.wannaverse.chimesdk.AudioDeviceType.SPEAKER","location":"chime-sdk/com.wannaverse.chimesdk/-audio-device-type/-s-p-e-a-k-e-r/index.html","searchKeys":["SPEAKER","SPEAKER","com.wannaverse.chimesdk.AudioDeviceType.SPEAKER"]},{"name":"UNKNOWN","description":"com.wannaverse.chimesdk.AudioDeviceType.UNKNOWN","location":"chime-sdk/com.wannaverse.chimesdk/-audio-device-type/-u-n-k-n-o-w-n/index.html","searchKeys":["UNKNOWN","UNKNOWN","com.wannaverse.chimesdk.AudioDeviceType.UNKNOWN"]},{"name":"WIRED_HEADSET","description":"com.wannaverse.chimesdk.AudioDeviceType.WIRED_HEADSET","location":"chime-sdk/com.wannaverse.chimesdk/-audio-device-type/-w-i-r-e-d_-h-e-a-d-s-e-t/index.html","searchKeys":["WIRED_HEADSET","WIRED_HEADSET","com.wannaverse.chimesdk.AudioDeviceType.WIRED_HEADSET"]},{"name":"abstract fun onAttendeesDropped(attendees: List<Attendee>)","description":"com.wannaverse.chimesdk.RealTimeEventListener.onAttendeesDropped","location":"chime-sdk/com.wannaverse.chimesdk/-real-time-event-listener/on-attendees-dropped.html","searchKeys":["onAttendeesDropped","abstract fun onAttendeesDropped(attendees: List<Attendee>)","com.wannaverse.chimesdk.RealTimeEventListener.onAttendeesDropped"]},{"name":"abstract fun onAttendeesJoined(attendees: List<Attendee>)","description":"com.wannaverse.chimesdk.RealTimeEventListener.onAttendeesJoined","location":"chime-sdk/com.wannaverse.chimesdk/-real-time-event-listener/on-attendees-joined.html","searchKeys":["onAttendeesJoined","abstract fun onAttendeesJoined(attendees: List<Attendee>)","com.wannaverse.chimesdk.RealTimeEventListener.onAttendeesJoined"]},{"name":"abstract fun onAttendeesLeft(attendees: List<Attendee>)","description":"com.wannaverse.chimesdk.RealTimeEventListener.onAttendeesLeft","location":"chime-sdk/com.wannaverse.chimesdk/-real-time-event-listener/on-attendees-left.html","searchKeys":["onAttendeesLeft","abstract fun onAttendeesLeft(attendees: List<Attendee>)","com.wannaverse.chimesdk.RealTimeEventListener.onAttendeesLeft"]},{"name":"abstract fun onAttendeesMuted(attendees: List<Attendee>)","description":"com.wannaverse.chimesdk.RealTimeEventListener.onAttendeesMuted","location":"chime-sdk/com.wannaverse.chimesdk/-real-time-event-listener/on-attendees-muted.html","searchKeys":["onAttendeesMuted","abstract fun onAttendeesMuted(attendees: List<Attendee>)","com.wannaverse.chimesdk.RealTimeEventListener.onAttendeesMuted"]},{"name":"abstract fun onAttendeesUnmuted(attendees: List<Attendee>)","description":"com.wannaverse.chimesdk.RealTimeEventListener.onAttendeesUnmuted","location":"chime-sdk/com.wannaverse.chimesdk/-real-time-event-listener/on-attendees-unmuted.html","searchKeys":["onAttendeesUnmuted","abstract fun onAttendeesUnmuted(attendees: List<Attendee>)","com.wannaverse.chimesdk.RealTimeEventListener.onAttendeesUnmuted"]},{"name":"abstract fun onAudioDevicesUpdated(audioDevices: List<AudioDevice>, selectedDevice: AudioDevice?)","description":"com.wannaverse.chimesdk.RealTimeEventListener.onAudioDevicesUpdated","location":"chime-sdk/com.wannaverse.chimesdk/-real-time-event-listener/on-audio-devices-updated.html","searchKeys":["onAudioDevicesUpdated","abstract fun onAudioDevicesUpdated(audioDevices: List<AudioDevice>, selectedDevice: AudioDevice?)","com.wannaverse.chimesdk.RealTimeEventListener.onAudioDevicesUpdated"]},{"name":"abstract fun onSignalStrengthChanged(attendee: Attendee, signal: Int)","description":"com.wannaverse.chimesdk.RealTimeEventListener.onSignalStrengthChanged","location":"chime-sdk/com.wannaverse.chimesdk/-real-time-event-listener/on-signal-strength-changed.html","searchKeys":["onSignalStrengthChanged","abstract fun onSignalStrengthChanged(attendee: Attendee, signal: Int)","com.wannaverse.chimesdk.RealTimeEventListener.onSignalStrengthChanged"]},{"name":"abstract fun onVolumeChanged(attendee: Attendee, volume: Int)","description":"com.wannaverse.chimesdk.RealTimeEventListener.onVolumeChanged","location":"chime-sdk/com.wannaverse.chimesdk/-real-time-event-listener/on-volume-changed.html","searchKeys":["onVolumeChanged","abstract fun onVolumeChanged(attendee: Attendee, volume: Int)","com.wannaverse.chimesdk.RealTimeEventListener.onVolumeChanged"]},{"name":"actual fun LocalVideoView(modifier: <Error class: unknown class>, cameraFacing: <Error class: unknown class>, isOnTop: Boolean): <Error class: unknown class>","description":"com.wannaverse.chimesdk.ChimeSDK.LocalVideoView","location":"chime-sdk/com.wannaverse.chimesdk/-chime-s-d-k/-local-video-view.html","searchKeys":["LocalVideoView","actual fun LocalVideoView(modifier: <Error class: unknown class>, cameraFacing: <Error class: unknown class>, isOnTop: Boolean): <Error class: unknown class>","com.wannaverse.chimesdk.ChimeSDK.LocalVideoView"]},{"name":"actual fun RemoteVideoView(modifier: <Error class: unknown class>, tileId: Int, isOnTop: Boolean): <Error class: unknown class>","description":"com.wannaverse.chimesdk.ChimeSDK.RemoteVideoView","location":"chime-sdk/com.wannaverse.chimesdk/-chime-s-d-k/-remote-video-view.html","searchKeys":["RemoteVideoView","actual fun RemoteVideoView(modifier: <Error class: unknown class>, tileId: Int, isOnTop: Boolean): <Error class: unknown class>","com.wannaverse.chimesdk.ChimeSDK.RemoteVideoView"]},{"name":"actual fun joinMeeting(realTimeListener: <Error class: unknown class>, onActiveSpeakersChanged: (Set<String>) -> Unit, onConnectionStatusChanged: (<Error class: unknown class>) -> Unit, onRemoteVideoAvailable: (Boolean, Int) -> Unit, onCameraSendAvailable: (Boolean) -> Unit, onSessionError: (String, Boolean) -> Unit, onVideoNeedsRestart: () -> Unit, selectedAudioInputDevice: String?, isJoiningOnMute: Boolean, onLocalTileAdded: (Int) -> Unit, onLocalTileRemoved: () -> Unit, onRemoteTileAdded: (Int) -> Unit, onRemoteTileRemoved: () -> Unit)","description":"com.wannaverse.chimesdk.ChimeSDK.joinMeeting","location":"chime-sdk/com.wannaverse.chimesdk/-chime-s-d-k/join-meeting.html","searchKeys":["joinMeeting","actual fun joinMeeting(realTimeListener: <Error class: unknown class>, onActiveSpeakersChanged: (Set<String>) -> Unit, onConnectionStatusChanged: (<Error class: unknown class>) -> Unit, onRemoteVideoAvailable: (Boolean, Int) -> Unit, onCameraSendAvailable: (Boolean) -> Unit, onSessionError: (String, Boolean) -> Unit, onVideoNeedsRestart: () -> Unit, selectedAudioInputDevice: String?, isJoiningOnMute: Boolean, onLocalTileAdded: (Int) -> Unit, onLocalTileRemoved: () -> Unit, onRemoteTileAdded: (Int) -> Unit, onRemoteTileRemoved: () -> Unit)","com.wannaverse.chimesdk.ChimeSDK.joinMeeting"]},{"name":"actual fun subscribeToTopic(topic: String, listener: (<Error class: unknown class>) -> Unit)","description":"com.wannaverse.chimesdk.ChimeSDK.subscribeToTopic","location":"chime-sdk/com.wannaverse.chimesdk/-chime-s-d-k/subscribe-to-topic.html","searchKeys":["subscribeToTopic","actual fun subscribeToTopic(topic: String, listener: (<Error class: unknown class>) -> Unit)","com.wannaverse.chimesdk.ChimeSDK.subscribeToTopic"]},{"name":"actual fun switchAudioDevice(device: <Error class: unknown class>?)","description":"com.wannaverse.chimesdk.ChimeSDK.switchAudioDevice","location":"chime-sdk/com.wannaverse.chimesdk/-chime-s-d-k/switch-audio-device.html","searchKeys":["switchAudioDevice","actual fun switchAudioDevice(device: <Error class: unknown class>?)","com.wannaverse.chimesdk.ChimeSDK.switchAudioDevice"]},{"name":"class ActiveSpeakerObserverImpl(val onActiveSpeakersChanged: (Set<String>) -> Unit)","description":"com.wannaverse.chimesdk.ActiveSpeakerObserverImpl","location":"chime-sdk/com.wannaverse.chimesdk/[ios]-active-speaker-observer-impl/index.html","searchKeys":["ActiveSpeakerObserverImpl","class ActiveSpeakerObserverImpl(val onActiveSpeakersChanged: (Set<String>) -> Unit)","com.wannaverse.chimesdk.ActiveSpeakerObserverImpl"]},{"name":"class ActiveSpeakerObserverImpl(val onActiveSpeakersChanged: (Set<String>) -> Unit) : ActiveSpeakerObserver","description":"com.wannaverse.chimesdk.ActiveSpeakerObserverImpl","location":"chime-sdk/com.wannaverse.chimesdk/[android]-active-speaker-observer-impl/index.html","searchKeys":["ActiveSpeakerObserverImpl","class ActiveSpeakerObserverImpl(val onActiveSpeakersChanged: (Set<String>) -> Unit) : ActiveSpeakerObserver","com.wannaverse.chimesdk.ActiveSpeakerObserverImpl"]},{"name":"class AudioVideoObserverImpl(meetingSession: <Error class: unknown class>, onConnectionStatusChanged: (<Error class: unknown class>) -> Unit, onRemoteVideoAvailable: (isAvailable: Boolean, sourceCount: Int) -> Unit, onCameraSendAvailable: (available: Boolean) -> Unit, onSessionError: (message: String, isRecoverable: Boolean) -> Unit, onVideoNeedsRestart: () -> Unit, isJoiningOnMute: Boolean)","description":"com.wannaverse.chimesdk.AudioVideoObserverImpl","location":"chime-sdk/com.wannaverse.chimesdk/[ios]-audio-video-observer-impl/index.html","searchKeys":["AudioVideoObserverImpl","class AudioVideoObserverImpl(meetingSession: <Error class: unknown class>, onConnectionStatusChanged: (<Error class: unknown class>) -> Unit, onRemoteVideoAvailable: (isAvailable: Boolean, sourceCount: Int) -> Unit, onCameraSendAvailable: (available: Boolean) -> Unit, onSessionError: (message: String, isRecoverable: Boolean) -> Unit, onVideoNeedsRestart: () -> Unit, isJoiningOnMute: Boolean)","com.wannaverse.chimesdk.AudioVideoObserverImpl"]},{"name":"class AudioVideoObserverImpl(meetingSession: MeetingSession, onConnectionStatusChanged: (ConnectionStatus) -> Unit, onRemoteVideoAvailable: (isAvailable: Boolean, sourceCount: Int) -> Unit, onCameraSendAvailable: (available: Boolean) -> Unit, onSessionError: (message: String, isRecoverable: Boolean) -> Unit, onVideoNeedsRestart: () -> Unit, isJoiningOnMute: Boolean) : AudioVideoObserver","description":"com.wannaverse.chimesdk.AudioVideoObserverImpl","location":"chime-sdk/com.wannaverse.chimesdk/[android]-audio-video-observer-impl/index.html","searchKeys":["AudioVideoObserverImpl","class AudioVideoObserverImpl(meetingSession: MeetingSession, onConnectionStatusChanged: (ConnectionStatus) -> Unit, onRemoteVideoAvailable: (isAvailable: Boolean, sourceCount: Int) -> Unit, onCameraSendAvailable: (available: Boolean) -> Unit, onSessionError: (message: String, isRecoverable: Boolean) -> Unit, onVideoNeedsRestart: () -> Unit, isJoiningOnMute: Boolean) : AudioVideoObserver","com.wannaverse.chimesdk.AudioVideoObserverImpl"]},{"name":"class DataMessageObserverImpl(meetingSession: <Error class: unknown class>)","description":"com.wannaverse.chimesdk.DataMessageObserverImpl","location":"chime-sdk/com.wannaverse.chimesdk/[ios]-data-message-observer-impl/index.html","searchKeys":["DataMessageObserverImpl","class DataMessageObserverImpl(meetingSession: <Error class: unknown class>)","com.wannaverse.chimesdk.DataMessageObserverImpl"]},{"name":"class DataMessageObserverImpl(meetingSession: MeetingSession) : DataMessageObserver","description":"com.wannaverse.chimesdk.DataMessageObserverImpl","location":"chime-sdk/com.wannaverse.chimesdk/[android]-data-message-observer-impl/index.html","searchKeys":["DataMessageObserverImpl","class DataMessageObserverImpl(meetingSession: MeetingSession) : DataMessageObserver","com.wannaverse.chimesdk.DataMessageObserverImpl"]},{"name":"class DeviceObserverImpl(meetingSession: <Error class: unknown class>, realTimeEventListener: <Error class: unknown class>)","description":"com.wannaverse.chimesdk.DeviceObserverImpl","location":"chime-sdk/com.wannaverse.chimesdk/[ios]-device-observer-impl/index.html","searchKeys":["DeviceObserverImpl","class DeviceObserverImpl(meetingSession: <Error class: unknown class>, realTimeEventListener: <Error class: unknown class>)","com.wannaverse.chimesdk.DeviceObserverImpl"]},{"name":"class DeviceObserverImpl(meetingSession: DefaultMeetingSession, realTimeEventListener: RealTimeEventListener) : DeviceChangeObserver","description":"com.wannaverse.chimesdk.DeviceObserverImpl","location":"chime-sdk/com.wannaverse.chimesdk/[android]-device-observer-impl/index.html","searchKeys":["DeviceObserverImpl","class DeviceObserverImpl(meetingSession: DefaultMeetingSession, realTimeEventListener: RealTimeEventListener) : DeviceChangeObserver","com.wannaverse.chimesdk.DeviceObserverImpl"]},{"name":"class RealTimeObserverImpl(val listener: <Error class: unknown class>)","description":"com.wannaverse.chimesdk.RealTimeObserverImpl","location":"chime-sdk/com.wannaverse.chimesdk/[ios]-real-time-observer-impl/index.html","searchKeys":["RealTimeObserverImpl","class RealTimeObserverImpl(val listener: <Error class: unknown class>)","com.wannaverse.chimesdk.RealTimeObserverImpl"]},{"name":"class RealTimeObserverImpl(val listener: RealTimeEventListener) : RealtimeObserver","description":"com.wannaverse.chimesdk.RealTimeObserverImpl","location":"chime-sdk/com.wannaverse.chimesdk/[android]-real-time-observer-impl/index.html","searchKeys":["RealTimeObserverImpl","class RealTimeObserverImpl(val listener: RealTimeEventListener) : RealtimeObserver","com.wannaverse.chimesdk.RealTimeObserverImpl"]},{"name":"class VideoTileObserverImpl(meetingSession: <Error class: unknown class>, onLocalTileAdded: (Int) -> Unit, onLocalTileRemoved: () -> Unit, onRemoteTileAdded: (Int) -> Unit, onRemoteTileRemoved: () -> Unit)","description":"com.wannaverse.chimesdk.VideoTileObserverImpl","location":"chime-sdk/com.wannaverse.chimesdk/[ios]-video-tile-observer-impl/index.html","searchKeys":["VideoTileObserverImpl","class VideoTileObserverImpl(meetingSession: <Error class: unknown class>, onLocalTileAdded: (Int) -> Unit, onLocalTileRemoved: () -> Unit, onRemoteTileAdded: (Int) -> Unit, onRemoteTileRemoved: () -> Unit)","com.wannaverse.chimesdk.VideoTileObserverImpl"]},{"name":"class VideoTileObserverImpl(meetingSession: MeetingSession, onLocalTileAdded: (Int) -> Unit, onLocalTileRemoved: () -> Unit, onRemoteTileAdded: (Int) -> Unit, onRemoteTileRemoved: () -> Unit) : VideoTileObserver","description":"com.wannaverse.chimesdk.VideoTileObserverImpl","location":"chime-sdk/com.wannaverse.chimesdk/[android]-video-tile-observer-impl/index.html","searchKeys":["VideoTileObserverImpl","class VideoTileObserverImpl(meetingSession: MeetingSession, onLocalTileAdded: (Int) -> Unit, onLocalTileRemoved: () -> Unit, onRemoteTileAdded: (Int) -> Unit, onRemoteTileRemoved: () -> Unit) : VideoTileObserver","com.wannaverse.chimesdk.VideoTileObserverImpl"]},{"name":"constructor(attendeeId: String, externalUserId: String)","description":"com.wannaverse.chimesdk.Attendee.Attendee","location":"chime-sdk/com.wannaverse.chimesdk/-attendee/-attendee.html","searchKeys":["Attendee","constructor(attendeeId: String, externalUserId: String)","com.wannaverse.chimesdk.Attendee.Attendee"]},{"name":"constructor(externalMeetingId: String = \"\", meetingId: String = \"\", audioHostURL: String = \"\", audioFallbackURL: String = \"\", turnControlURL: String = \"\", signalingURL: String = \"\", ingestionURL: String = \"\", attendeeId: String = \"\", externalUserId: String = \"\", joinToken: String = \"\")","description":"com.wannaverse.chimesdk.MeetingInformation.MeetingInformation","location":"chime-sdk/com.wannaverse.chimesdk/-meeting-information/-meeting-information.html","searchKeys":["MeetingInformation","constructor(externalMeetingId: String = \"\", meetingId: String = \"\", audioHostURL: String = \"\", audioFallbackURL: String = \"\", turnControlURL: String = \"\", signalingURL: String = \"\", ingestionURL: String = \"\", attendeeId: String = \"\", externalUserId: String = \"\", joinToken: String = \"\")","com.wannaverse.chimesdk.MeetingInformation.MeetingInformation"]},{"name":"constructor(listener: <Error class: unknown class>)","description":"com.wannaverse.chimesdk.RealTimeObserverImpl.RealTimeObserverImpl","location":"chime-sdk/com.wannaverse.chimesdk/[ios]-real-time-observer-impl/-real-time-observer-impl.html","searchKeys":["RealTimeObserverImpl","constructor(listener: <Error class: unknown class>)","com.wannaverse.chimesdk.RealTimeObserverImpl.RealTimeObserverImpl"]},{"name":"constructor(listener: RealTimeEventListener)","description":"com.wannaverse.chimesdk.RealTimeObserverImpl.RealTimeObserverImpl","location":"chime-sdk/com.wannaverse.chimesdk/[android]-real-time-observer-impl/-real-time-observer-impl.html","searchKeys":["RealTimeObserverImpl","constructor(listener: RealTimeEventListener)","com.wannaverse.chimesdk.RealTimeObserverImpl.RealTimeObserverImpl"]},{"name":"constructor(meetingSession: <Error class: unknown class>)","description":"com.wannaverse.chimesdk.ChimeSDK.ChimeSDK","location":"chime-sdk/com.wannaverse.chimesdk/-chime-s-d-k/-chime-s-d-k.html","searchKeys":["ChimeSDK","constructor(meetingSession: <Error class: unknown class>)","com.wannaverse.chimesdk.ChimeSDK.ChimeSDK"]},{"name":"constructor(meetingSession: <Error class: unknown class>)","description":"com.wannaverse.chimesdk.DataMessageObserverImpl.DataMessageObserverImpl","location":"chime-sdk/com.wannaverse.chimesdk/[ios]-data-message-observer-impl/-data-message-observer-impl.html","searchKeys":["DataMessageObserverImpl","constructor(meetingSession: <Error class: unknown class>)","com.wannaverse.chimesdk.DataMessageObserverImpl.DataMessageObserverImpl"]},{"name":"constructor(meetingSession: <Error class: unknown class>, onConnectionStatusChanged: (<Error class: unknown class>) -> Unit, onRemoteVideoAvailable: (isAvailable: Boolean, sourceCount: Int) -> Unit, onCameraSendAvailable: (available: Boolean) -> Unit, onSessionError: (message: String, isRecoverable: Boolean) -> Unit, onVideoNeedsRestart: () -> Unit, isJoiningOnMute: Boolean)","description":"com.wannaverse.chimesdk.AudioVideoObserverImpl.AudioVideoObserverImpl","location":"chime-sdk/com.wannaverse.chimesdk/[ios]-audio-video-observer-impl/-audio-video-observer-impl.html","searchKeys":["AudioVideoObserverImpl","constructor(meetingSession: <Error class: unknown class>, onConnectionStatusChanged: (<Error class: unknown class>) -> Unit, onRemoteVideoAvailable: (isAvailable: Boolean, sourceCount: Int) -> Unit, onCameraSendAvailable: (available: Boolean) -> Unit, onSessionError: (message: String, isRecoverable: Boolean) -> Unit, onVideoNeedsRestart: () -> Unit, isJoiningOnMute: Boolean)","com.wannaverse.chimesdk.AudioVideoObserverImpl.AudioVideoObserverImpl"]},{"name":"constructor(meetingSession: <Error class: unknown class>, onLocalTileAdded: (Int) -> Unit, onLocalTileRemoved: () -> Unit, onRemoteTileAdded: (Int) -> Unit, onRemoteTileRemoved: () -> Unit)","description":"com.wannaverse.chimesdk.VideoTileObserverImpl.VideoTileObserverImpl","location":"chime-sdk/com.wannaverse.chimesdk/[ios]-video-tile-observer-impl/-video-tile-observer-impl.html","searchKeys":["VideoTileObserverImpl","constructor(meetingSession: <Error class: unknown class>, onLocalTileAdded: (Int) -> Unit, onLocalTileRemoved: () -> Unit, onRemoteTileAdded: (Int) -> Unit, onRemoteTileRemoved: () -> Unit)","com.wannaverse.chimesdk.VideoTileObserverImpl.VideoTileObserverImpl"]},{"name":"constructor(meetingSession: <Error class: unknown class>, realTimeEventListener: <Error class: unknown class>)","description":"com.wannaverse.chimesdk.DeviceObserverImpl.DeviceObserverImpl","location":"chime-sdk/com.wannaverse.chimesdk/[ios]-device-observer-impl/-device-observer-impl.html","searchKeys":["DeviceObserverImpl","constructor(meetingSession: <Error class: unknown class>, realTimeEventListener: <Error class: unknown class>)","com.wannaverse.chimesdk.DeviceObserverImpl.DeviceObserverImpl"]},{"name":"constructor(meetingSession: DefaultMeetingSession, eventAnalyticsController: DefaultEventAnalyticsController, eglCoreFactory: DefaultEglCoreFactory)","description":"com.wannaverse.chimesdk.ChimeSDK.ChimeSDK","location":"chime-sdk/com.wannaverse.chimesdk/-chime-s-d-k/-chime-s-d-k.html","searchKeys":["ChimeSDK","constructor(meetingSession: DefaultMeetingSession, eventAnalyticsController: DefaultEventAnalyticsController, eglCoreFactory: DefaultEglCoreFactory)","com.wannaverse.chimesdk.ChimeSDK.ChimeSDK"]},{"name":"constructor(meetingSession: DefaultMeetingSession, realTimeEventListener: RealTimeEventListener)","description":"com.wannaverse.chimesdk.DeviceObserverImpl.DeviceObserverImpl","location":"chime-sdk/com.wannaverse.chimesdk/[android]-device-observer-impl/-device-observer-impl.html","searchKeys":["DeviceObserverImpl","constructor(meetingSession: DefaultMeetingSession, realTimeEventListener: RealTimeEventListener)","com.wannaverse.chimesdk.DeviceObserverImpl.DeviceObserverImpl"]},{"name":"constructor(meetingSession: MeetingSession)","description":"com.wannaverse.chimesdk.DataMessageObserverImpl.DataMessageObserverImpl","location":"chime-sdk/com.wannaverse.chimesdk/[android]-data-message-observer-impl/-data-message-observer-impl.html","searchKeys":["DataMessageObserverImpl","constructor(meetingSession: MeetingSession)","com.wannaverse.chimesdk.DataMessageObserverImpl.DataMessageObserverImpl"]},{"name":"constructor(meetingSession: MeetingSession, onConnectionStatusChanged: (ConnectionStatus) -> Unit, onRemoteVideoAvailable: (isAvailable: Boolean, sourceCount: Int) -> Unit, onCameraSendAvailable: (available: Boolean) -> Unit, onSessionError: (message: String, isRecoverable: Boolean) -> Unit, onVideoNeedsRestart: () -> Unit, isJoiningOnMute: Boolean)","description":"com.wannaverse.chimesdk.AudioVideoObserverImpl.AudioVideoObserverImpl","location":"chime-sdk/com.wannaverse.chimesdk/[android]-audio-video-observer-impl/-audio-video-observer-impl.html","searchKeys":["AudioVideoObserverImpl","constructor(meetingSession: MeetingSession, onConnectionStatusChanged: (ConnectionStatus) -> Unit, onRemoteVideoAvailable: (isAvailable: Boolean, sourceCount: Int) -> Unit, onCameraSendAvailable: (available: Boolean) -> Unit, onSessionError: (message: String, isRecoverable: Boolean) -> Unit, onVideoNeedsRestart: () -> Unit, isJoiningOnMute: Boolean)","com.wannaverse.chimesdk.AudioVideoObserverImpl.AudioVideoObserverImpl"]},{"name":"constructor(meetingSession: MeetingSession, onLocalTileAdded: (Int) -> Unit, onLocalTileRemoved: () -> Unit, onRemoteTileAdded: (Int) -> Unit, onRemoteTileRemoved: () -> Unit)","description":"com.wannaverse.chimesdk.VideoTileObserverImpl.VideoTileObserverImpl","location":"chime-sdk/com.wannaverse.chimesdk/[android]-video-tile-observer-impl/-video-tile-observer-impl.html","searchKeys":["VideoTileObserverImpl","constructor(meetingSession: MeetingSession, onLocalTileAdded: (Int) -> Unit, onLocalTileRemoved: () -> Unit, onRemoteTileAdded: (Int) -> Unit, onRemoteTileRemoved: () -> Unit)","com.wannaverse.chimesdk.VideoTileObserverImpl.VideoTileObserverImpl"]},{"name":"constructor(onActiveSpeakersChanged: (Set<String>) -> Unit)","description":"com.wannaverse.chimesdk.ActiveSpeakerObserverImpl.ActiveSpeakerObserverImpl","location":"chime-sdk/com.wannaverse.chimesdk/[android]-active-speaker-observer-impl/-active-speaker-observer-impl.html","searchKeys":["ActiveSpeakerObserverImpl","constructor(onActiveSpeakersChanged: (Set<String>) -> Unit)","com.wannaverse.chimesdk.ActiveSpeakerObserverImpl.ActiveSpeakerObserverImpl"]},{"name":"constructor(onActiveSpeakersChanged: (Set<String>) -> Unit)","description":"com.wannaverse.chimesdk.ActiveSpeakerObserverImpl.ActiveSpeakerObserverImpl","location":"chime-sdk/com.wannaverse.chimesdk/[ios]-active-speaker-observer-impl/-active-speaker-observer-impl.html","searchKeys":["ActiveSpeakerObserverImpl","constructor(onActiveSpeakersChanged: (Set<String>) -> Unit)","com.wannaverse.chimesdk.ActiveSpeakerObserverImpl.ActiveSpeakerObserverImpl"]},{"name":"constructor(senderId: String, content: String, timestamp: Long)","description":"com.wannaverse.chimesdk.ChimeMessage.ChimeMessage","location":"chime-sdk/com.wannaverse.chimesdk/-chime-message/-chime-message.html","searchKeys":["ChimeMessage","constructor(senderId: String, content: String, timestamp: Long)","com.wannaverse.chimesdk.ChimeMessage.ChimeMessage"]},{"name":"constructor(topic: String, senderId: String, content: String, timestamp: Long)","description":"com.wannaverse.chimesdk.TextMessage.TextMessage","location":"chime-sdk/com.wannaverse.chimesdk/-text-message/-text-message.html","searchKeys":["TextMessage","constructor(topic: String, senderId: String, content: String, timestamp: Long)","com.wannaverse.chimesdk.TextMessage.TextMessage"]},{"name":"constructor(type: AudioDeviceType, label: String)","description":"com.wannaverse.chimesdk.AudioDevice.AudioDevice","location":"chime-sdk/com.wannaverse.chimesdk/-audio-device/-audio-device.html","searchKeys":["AudioDevice","constructor(type: AudioDeviceType, label: String)","com.wannaverse.chimesdk.AudioDevice.AudioDevice"]},{"name":"data class Attendee(val attendeeId: String, val externalUserId: String)","description":"com.wannaverse.chimesdk.Attendee","location":"chime-sdk/com.wannaverse.chimesdk/-attendee/index.html","searchKeys":["Attendee","data class Attendee(val attendeeId: String, val externalUserId: String)","com.wannaverse.chimesdk.Attendee"]},{"name":"data class AudioDevice(val type: AudioDeviceType, val label: String)","description":"com.wannaverse.chimesdk.AudioDevice","location":"chime-sdk/com.wannaverse.chimesdk/-audio-device/index.html","searchKeys":["AudioDevice","data class AudioDevice(val type: AudioDeviceType, val label: String)","com.wannaverse.chimesdk.AudioDevice"]},{"name":"data class ChimeMessage(val senderId: String, val content: String, val timestamp: Long)","description":"com.wannaverse.chimesdk.ChimeMessage","location":"chime-sdk/com.wannaverse.chimesdk/-chime-message/index.html","searchKeys":["ChimeMessage","data class ChimeMessage(val senderId: String, val content: String, val timestamp: Long)","com.wannaverse.chimesdk.ChimeMessage"]},{"name":"data class MeetingInformation(val externalMeetingId: String = \"\", val meetingId: String = \"\", val audioHostURL: String = \"\", val audioFallbackURL: String = \"\", val turnControlURL: String = \"\", val signalingURL: String = \"\", val ingestionURL: String = \"\", val attendeeId: String = \"\", val externalUserId: String = \"\", val joinToken: String = \"\")","description":"com.wannaverse.chimesdk.MeetingInformation","location":"chime-sdk/com.wannaverse.chimesdk/-meeting-information/index.html","searchKeys":["MeetingInformation","data class MeetingInformation(val externalMeetingId: String = \"\", val meetingId: String = \"\", val audioHostURL: String = \"\", val audioFallbackURL: String = \"\", val turnControlURL: String = \"\", val signalingURL: String = \"\", val ingestionURL: String = \"\", val attendeeId: String = \"\", val externalUserId: String = \"\", val joinToken: String = \"\")","com.wannaverse.chimesdk.MeetingInformation"]},{"name":"data class TextMessage(val topic: String, val senderId: String, val content: String, val timestamp: Long)","description":"com.wannaverse.chimesdk.TextMessage","location":"chime-sdk/com.wannaverse.chimesdk/-text-message/index.html","searchKeys":["TextMessage","data class TextMessage(val topic: String, val senderId: String, val content: String, val timestamp: Long)","com.wannaverse.chimesdk.TextMessage"]},{"name":"enum AudioDeviceType : Enum<AudioDeviceType> ","description":"com.wannaverse.chimesdk.AudioDeviceType","location":"chime-sdk/com.wannaverse.chimesdk/-audio-device-type/index.html","searchKeys":["AudioDeviceType","enum AudioDeviceType : Enum<AudioDeviceType> ","com.wannaverse.chimesdk.AudioDeviceType"]},{"name":"enum CameraFacing : Enum<CameraFacing> ","description":"com.wannaverse.chimesdk.CameraFacing","location":"chime-sdk/com.wannaverse.chimesdk/-camera-facing/index.html","searchKeys":["CameraFacing","enum CameraFacing : Enum<CameraFacing> ","com.wannaverse.chimesdk.CameraFacing"]},{"name":"enum ConnectionStatus : Enum<ConnectionStatus> ","description":"com.wannaverse.chimesdk.ConnectionStatus","location":"chime-sdk/com.wannaverse.chimesdk/-connection-status/index.html","searchKeys":["ConnectionStatus","enum ConnectionStatus : Enum<ConnectionStatus> ","com.wannaverse.chimesdk.ConnectionStatus"]},{"name":"expect class ChimeSDK","description":"com.wannaverse.chimesdk.ChimeSDK","location":"chime-sdk/com.wannaverse.chimesdk/-chime-s-d-k/index.html","searchKeys":["ChimeSDK","expect class ChimeSDK","com.wannaverse.chimesdk.ChimeSDK"]},{"name":"expect fun LocalVideoView(modifier: Modifier, cameraFacing: CameraFacing, isOnTop: Boolean)","description":"com.wannaverse.chimesdk.ChimeSDK.LocalVideoView","location":"chime-sdk/com.wannaverse.chimesdk/-chime-s-d-k/-local-video-view.html","searchKeys":["LocalVideoView","expect fun LocalVideoView(modifier: Modifier, cameraFacing: CameraFacing, isOnTop: Boolean)","com.wannaverse.chimesdk.ChimeSDK.LocalVideoView"]},{"name":"expect fun RemoteVideoView(modifier: Modifier, tileId: Int, isOnTop: Boolean)","description":"com.wannaverse.chimesdk.ChimeSDK.RemoteVideoView","location":"chime-sdk/com.wannaverse.chimesdk/-chime-s-d-k/-remote-video-view.html","searchKeys":["RemoteVideoView","expect fun RemoteVideoView(modifier: Modifier, tileId: Int, isOnTop: Boolean)","com.wannaverse.chimesdk.ChimeSDK.RemoteVideoView"]},{"name":"expect fun createSession(externalMeetingId: String, meetingId: String, audioHostURL: String, audioFallbackURL: String, turnControlURL: String, signalingURL: String, ingestionURL: String, attendeeId: String, externalUserId: String, joinToken: String): ChimeSDK","description":"com.wannaverse.chimesdk.ChimeSDK.Companion.createSession","location":"chime-sdk/com.wannaverse.chimesdk/-chime-s-d-k/-companion/create-session.html","searchKeys":["createSession","expect fun createSession(externalMeetingId: String, meetingId: String, audioHostURL: String, audioFallbackURL: String, turnControlURL: String, signalingURL: String, ingestionURL: String, attendeeId: String, externalUserId: String, joinToken: String): ChimeSDK","com.wannaverse.chimesdk.ChimeSDK.Companion.createSession"]},{"name":"expect fun getAvailableInputDevices(): List<AudioDevice>","description":"com.wannaverse.chimesdk.ChimeSDK.getAvailableInputDevices","location":"chime-sdk/com.wannaverse.chimesdk/-chime-s-d-k/get-available-input-devices.html","searchKeys":["getAvailableInputDevices","expect fun getAvailableInputDevices(): List<AudioDevice>","com.wannaverse.chimesdk.ChimeSDK.getAvailableInputDevices"]},{"name":"expect fun getAvailableOutputDevices(): List<AudioDevice>","description":"com.wannaverse.chimesdk.ChimeSDK.getAvailableOutputDevices","location":"chime-sdk/com.wannaverse.chimesdk/-chime-s-d-k/get-available-output-devices.html","searchKeys":["getAvailableOutputDevices","expect fun getAvailableOutputDevices(): List<AudioDevice>","com.wannaverse.chimesdk.ChimeSDK.getAvailableOutputDevices"]},{"name":"expect fun joinMeeting(realTimeListener: RealTimeEventListener, onActiveSpeakersChanged: (Set<String>) -> Unit, onConnectionStatusChanged: (ConnectionStatus) -> Unit, onRemoteVideoAvailable: (Boolean, Int) -> Unit, onCameraSendAvailable: (Boolean) -> Unit, onSessionError: (String, Boolean) -> Unit, onVideoNeedsRestart: () -> Unit, selectedAudioInputDevice: String?, isJoiningOnMute: Boolean, onLocalTileAdded: (Int) -> Unit, onLocalTileRemoved: () -> Unit, onRemoteTileAdded: (Int) -> Unit, onRemoteTileRemoved: () -> Unit)","description":"com.wannaverse.chimesdk.ChimeSDK.joinMeeting","location":"chime-sdk/com.wannaverse.chimesdk/-chime-s-d-k/join-meeting.html","searchKeys":["joinMeeting","expect fun joinMeeting(realTimeListener: RealTimeEventListener, onActiveSpeakersChanged: (Set<String>) -> Unit, onConnectionStatusChanged: (ConnectionStatus) -> Unit, onRemoteVideoAvailable: (Boolean, Int) -> Unit, onCameraSendAvailable: (Boolean) -> Unit, onSessionError: (String, Boolean) -> Unit, onVideoNeedsRestart: () -> Unit, selectedAudioInputDevice: String?, isJoiningOnMute: Boolean, onLocalTileAdded: (Int) -> Unit, onLocalTileRemoved: () -> Unit, onRemoteTileAdded: (Int) -> Unit, onRemoteTileRemoved: () -> Unit)","com.wannaverse.chimesdk.ChimeSDK.joinMeeting"]},{"name":"expect fun leaveMeeting()","description":"com.wannaverse.chimesdk.ChimeSDK.leaveMeeting","location":"chime-sdk/com.wannaverse.chimesdk/-chime-s-d-k/leave-meeting.html","searchKeys":["leaveMeeting","expect fun leaveMeeting()","com.wannaverse.chimesdk.ChimeSDK.leaveMeeting"]},{"name":"expect fun sendRealtimeMessage(topic: String, data: String, lifetimeMs: Long = 0)","description":"com.wannaverse.chimesdk.ChimeSDK.sendRealtimeMessage","location":"chime-sdk/com.wannaverse.chimesdk/-chime-s-d-k/send-realtime-message.html","searchKeys":["sendRealtimeMessage","expect fun sendRealtimeMessage(topic: String, data: String, lifetimeMs: Long = 0)","com.wannaverse.chimesdk.ChimeSDK.sendRealtimeMessage"]},{"name":"expect fun setMute(shouldMute: Boolean): Boolean","description":"com.wannaverse.chimesdk.ChimeSDK.setMute","location":"chime-sdk/com.wannaverse.chimesdk/-chime-s-d-k/set-mute.html","searchKeys":["setMute","expect fun setMute(shouldMute: Boolean): Boolean","com.wannaverse.chimesdk.ChimeSDK.setMute"]},{"name":"expect fun startLocalVideo()","description":"com.wannaverse.chimesdk.ChimeSDK.startLocalVideo","location":"chime-sdk/com.wannaverse.chimesdk/-chime-s-d-k/start-local-video.html","searchKeys":["startLocalVideo","expect fun startLocalVideo()","com.wannaverse.chimesdk.ChimeSDK.startLocalVideo"]},{"name":"expect fun stopLocalVideo()","description":"com.wannaverse.chimesdk.ChimeSDK.stopLocalVideo","location":"chime-sdk/com.wannaverse.chimesdk/-chime-s-d-k/stop-local-video.html","searchKeys":["stopLocalVideo","expect fun stopLocalVideo()","com.wannaverse.chimesdk.ChimeSDK.stopLocalVideo"]},{"name":"expect fun subscribeToTopic(topic: String, listener: (ChimeMessage) -> Unit)","description":"com.wannaverse.chimesdk.ChimeSDK.subscribeToTopic","location":"chime-sdk/com.wannaverse.chimesdk/-chime-s-d-k/subscribe-to-topic.html","searchKeys":["subscribeToTopic","expect fun subscribeToTopic(topic: String, listener: (ChimeMessage) -> Unit)","com.wannaverse.chimesdk.ChimeSDK.subscribeToTopic"]},{"name":"expect fun switchAudioDevice(device: AudioDevice?)","description":"com.wannaverse.chimesdk.ChimeSDK.switchAudioDevice","location":"chime-sdk/com.wannaverse.chimesdk/-chime-s-d-k/switch-audio-device.html","searchKeys":["switchAudioDevice","expect fun switchAudioDevice(device: AudioDevice?)","com.wannaverse.chimesdk.ChimeSDK.switchAudioDevice"]},{"name":"expect fun switchCamera()","description":"com.wannaverse.chimesdk.ChimeSDK.switchCamera","location":"chime-sdk/com.wannaverse.chimesdk/-chime-s-d-k/switch-camera.html","searchKeys":["switchCamera","expect fun switchCamera()","com.wannaverse.chimesdk.ChimeSDK.switchCamera"]},{"name":"expect fun unsubscribeFromTopic(topic: String)","description":"com.wannaverse.chimesdk.ChimeSDK.unsubscribeFromTopic","location":"chime-sdk/com.wannaverse.chimesdk/-chime-s-d-k/unsubscribe-from-topic.html","searchKeys":["unsubscribeFromTopic","expect fun unsubscribeFromTopic(topic: String)","com.wannaverse.chimesdk.ChimeSDK.unsubscribeFromTopic"]},{"name":"expect object Companion","description":"com.wannaverse.chimesdk.ChimeSDK.Companion","location":"chime-sdk/com.wannaverse.chimesdk/-chime-s-d-k/-companion/index.html","searchKeys":["Companion","expect object Companion","com.wannaverse.chimesdk.ChimeSDK.Companion"]},{"name":"fun VideoTileView(tileId: Int, modifier: Modifier, cameraFacing: CameraFacing? = null, isOnTop: Boolean, meetingSession: DefaultMeetingSession, videoTileObserverImpl: VideoTileObserverImpl)","description":"com.wannaverse.chimesdk.composables.VideoTileView","location":"chime-sdk/com.wannaverse.chimesdk.composables/-video-tile-view.html","searchKeys":["VideoTileView","fun VideoTileView(tileId: Int, modifier: Modifier, cameraFacing: CameraFacing? = null, isOnTop: Boolean, meetingSession: DefaultMeetingSession, videoTileObserverImpl: VideoTileObserverImpl)","com.wannaverse.chimesdk.composables.VideoTileView"]},{"name":"fun addListener(topic: String, listener: (<Error class: unknown class>) -> Unit)","description":"com.wannaverse.chimesdk.DataMessageObserverImpl.addListener","location":"chime-sdk/com.wannaverse.chimesdk/[ios]-data-message-observer-impl/add-listener.html","searchKeys":["addListener","fun addListener(topic: String, listener: (<Error class: unknown class>) -> Unit)","com.wannaverse.chimesdk.DataMessageObserverImpl.addListener"]},{"name":"fun addListener(topic: String, listener: (ChimeMessage) -> Unit)","description":"com.wannaverse.chimesdk.DataMessageObserverImpl.addListener","location":"chime-sdk/com.wannaverse.chimesdk/[android]-data-message-observer-impl/add-listener.html","searchKeys":["addListener","fun addListener(topic: String, listener: (ChimeMessage) -> Unit)","com.wannaverse.chimesdk.DataMessageObserverImpl.addListener"]},{"name":"fun clearAll()","description":"com.wannaverse.chimesdk.VideoTileObserverImpl.clearAll","location":"chime-sdk/com.wannaverse.chimesdk/[android]-video-tile-observer-impl/clear-all.html","searchKeys":["clearAll","fun clearAll()","com.wannaverse.chimesdk.VideoTileObserverImpl.clearAll"]},{"name":"fun clearBoundView(tileId: Int): <Error class: unknown class>","description":"com.wannaverse.chimesdk.VideoTileObserverImpl.clearBoundView","location":"chime-sdk/com.wannaverse.chimesdk/[android]-video-tile-observer-impl/clear-bound-view.html","searchKeys":["clearBoundView","fun clearBoundView(tileId: Int): <Error class: unknown class>","com.wannaverse.chimesdk.VideoTileObserverImpl.clearBoundView"]},{"name":"fun clearListeners()","description":"com.wannaverse.chimesdk.DataMessageObserverImpl.clearListeners","location":"chime-sdk/com.wannaverse.chimesdk/[android]-data-message-observer-impl/clear-listeners.html","searchKeys":["clearListeners","fun clearListeners()","com.wannaverse.chimesdk.DataMessageObserverImpl.clearListeners"]},{"name":"fun clearListeners()","description":"com.wannaverse.chimesdk.DataMessageObserverImpl.clearListeners","location":"chime-sdk/com.wannaverse.chimesdk/[ios]-data-message-observer-impl/clear-listeners.html","searchKeys":["clearListeners","fun clearListeners()","com.wannaverse.chimesdk.DataMessageObserverImpl.clearListeners"]},{"name":"fun getRemoteView(tileId: Int): <Error class: unknown class>?","description":"com.wannaverse.chimesdk.VideoTileObserverImpl.getRemoteView","location":"chime-sdk/com.wannaverse.chimesdk/[ios]-video-tile-observer-impl/get-remote-view.html","searchKeys":["getRemoteView","fun getRemoteView(tileId: Int): <Error class: unknown class>?","com.wannaverse.chimesdk.VideoTileObserverImpl.getRemoteView"]},{"name":"fun isAlreadyBound(tileId: Int, view: Any): Boolean","description":"com.wannaverse.chimesdk.VideoTileObserverImpl.isAlreadyBound","location":"chime-sdk/com.wannaverse.chimesdk/[android]-video-tile-observer-impl/is-already-bound.html","searchKeys":["isAlreadyBound","fun isAlreadyBound(tileId: Int, view: Any): Boolean","com.wannaverse.chimesdk.VideoTileObserverImpl.isAlreadyBound"]},{"name":"fun rebindLocalView()","description":"com.wannaverse.chimesdk.VideoTileObserverImpl.rebindLocalView","location":"chime-sdk/com.wannaverse.chimesdk/[ios]-video-tile-observer-impl/rebind-local-view.html","searchKeys":["rebindLocalView","fun rebindLocalView()","com.wannaverse.chimesdk.VideoTileObserverImpl.rebindLocalView"]},{"name":"fun rebindRemoteView(tileId: Int)","description":"com.wannaverse.chimesdk.VideoTileObserverImpl.rebindRemoteView","location":"chime-sdk/com.wannaverse.chimesdk/[ios]-video-tile-observer-impl/rebind-remote-view.html","searchKeys":["rebindRemoteView","fun rebindRemoteView(tileId: Int)","com.wannaverse.chimesdk.VideoTileObserverImpl.rebindRemoteView"]},{"name":"fun removeListener(topic: String)","description":"com.wannaverse.chimesdk.DataMessageObserverImpl.removeListener","location":"chime-sdk/com.wannaverse.chimesdk/[android]-data-message-observer-impl/remove-listener.html","searchKeys":["removeListener","fun removeListener(topic: String)","com.wannaverse.chimesdk.DataMessageObserverImpl.removeListener"]},{"name":"fun removeListener(topic: String)","description":"com.wannaverse.chimesdk.DataMessageObserverImpl.removeListener","location":"chime-sdk/com.wannaverse.chimesdk/[ios]-data-message-observer-impl/remove-listener.html","searchKeys":["removeListener","fun removeListener(topic: String)","com.wannaverse.chimesdk.DataMessageObserverImpl.removeListener"]},{"name":"fun selectAudioDevice(device: <Error class: unknown class>)","description":"com.wannaverse.chimesdk.DeviceObserverImpl.selectAudioDevice","location":"chime-sdk/com.wannaverse.chimesdk/[ios]-device-observer-impl/select-audio-device.html","searchKeys":["selectAudioDevice","fun selectAudioDevice(device: <Error class: unknown class>)","com.wannaverse.chimesdk.DeviceObserverImpl.selectAudioDevice"]},{"name":"fun selectAudioDevice(device: MediaDevice)","description":"com.wannaverse.chimesdk.DeviceObserverImpl.selectAudioDevice","location":"chime-sdk/com.wannaverse.chimesdk/[android]-device-observer-impl/select-audio-device.html","searchKeys":["selectAudioDevice","fun selectAudioDevice(device: MediaDevice)","com.wannaverse.chimesdk.DeviceObserverImpl.selectAudioDevice"]},{"name":"fun updateBoundView(tileId: Int, view: Any): <Error class: unknown class>","description":"com.wannaverse.chimesdk.VideoTileObserverImpl.updateBoundView","location":"chime-sdk/com.wannaverse.chimesdk/[android]-video-tile-observer-impl/update-bound-view.html","searchKeys":["updateBoundView","fun updateBoundView(tileId: Int, view: Any): <Error class: unknown class>","com.wannaverse.chimesdk.VideoTileObserverImpl.updateBoundView"]},{"name":"fun valueOf(value: String): AudioDeviceType","description":"com.wannaverse.chimesdk.AudioDeviceType.valueOf","location":"chime-sdk/com.wannaverse.chimesdk/-audio-device-type/value-of.html","searchKeys":["valueOf","fun valueOf(value: String): AudioDeviceType","com.wannaverse.chimesdk.AudioDeviceType.valueOf"]},{"name":"fun valueOf(value: String): CameraFacing","description":"com.wannaverse.chimesdk.CameraFacing.valueOf","location":"chime-sdk/com.wannaverse.chimesdk/-camera-facing/value-of.html","searchKeys":["valueOf","fun valueOf(value: String): CameraFacing","com.wannaverse.chimesdk.CameraFacing.valueOf"]},{"name":"fun valueOf(value: String): ConnectionStatus","description":"com.wannaverse.chimesdk.ConnectionStatus.valueOf","location":"chime-sdk/com.wannaverse.chimesdk/-connection-status/value-of.html","searchKeys":["valueOf","fun valueOf(value: String): ConnectionStatus","com.wannaverse.chimesdk.ConnectionStatus.valueOf"]},{"name":"fun values(): Array<AudioDeviceType>","description":"com.wannaverse.chimesdk.AudioDeviceType.values","location":"chime-sdk/com.wannaverse.chimesdk/-audio-device-type/values.html","searchKeys":["values","fun values(): Array<AudioDeviceType>","com.wannaverse.chimesdk.AudioDeviceType.values"]},{"name":"fun values(): Array<CameraFacing>","description":"com.wannaverse.chimesdk.CameraFacing.values","location":"chime-sdk/com.wannaverse.chimesdk/-camera-facing/values.html","searchKeys":["values","fun values(): Array<CameraFacing>","com.wannaverse.chimesdk.CameraFacing.values"]},{"name":"fun values(): Array<ConnectionStatus>","description":"com.wannaverse.chimesdk.ConnectionStatus.values","location":"chime-sdk/com.wannaverse.chimesdk/-connection-status/values.html","searchKeys":["values","fun values(): Array<ConnectionStatus>","com.wannaverse.chimesdk.ConnectionStatus.values"]},{"name":"interface RealTimeEventListener","description":"com.wannaverse.chimesdk.RealTimeEventListener","location":"chime-sdk/com.wannaverse.chimesdk/-real-time-event-listener/index.html","searchKeys":["RealTimeEventListener","interface RealTimeEventListener","com.wannaverse.chimesdk.RealTimeEventListener"]},{"name":"lateinit var appContext: Context","description":"com.wannaverse.chimesdk.appContext","location":"chime-sdk/com.wannaverse.chimesdk/app-context.html","searchKeys":["appContext","lateinit var appContext: Context","com.wannaverse.chimesdk.appContext"]},{"name":"object Companion","description":"com.wannaverse.chimesdk.VideoTileObserverImpl.Companion","location":"chime-sdk/com.wannaverse.chimesdk/[android]-video-tile-observer-impl/-companion/index.html","searchKeys":["Companion","object Companion","com.wannaverse.chimesdk.VideoTileObserverImpl.Companion"]},{"name":"open fun activeSpeakerDidDetectWithAttendeeInfo(attendeeInfo: List<*>)","description":"com.wannaverse.chimesdk.ActiveSpeakerObserverImpl.activeSpeakerDidDetectWithAttendeeInfo","location":"chime-sdk/com.wannaverse.chimesdk/[ios]-active-speaker-observer-impl/active-speaker-did-detect-with-attendee-info.html","searchKeys":["activeSpeakerDidDetectWithAttendeeInfo","open fun activeSpeakerDidDetectWithAttendeeInfo(attendeeInfo: List<*>)","com.wannaverse.chimesdk.ActiveSpeakerObserverImpl.activeSpeakerDidDetectWithAttendeeInfo"]},{"name":"open fun activeSpeakerScoreDidChangeWithScores(scores: Map<Any?, *>): <Error class: unknown class>","description":"com.wannaverse.chimesdk.ActiveSpeakerObserverImpl.activeSpeakerScoreDidChangeWithScores","location":"chime-sdk/com.wannaverse.chimesdk/[ios]-active-speaker-observer-impl/active-speaker-score-did-change-with-scores.html","searchKeys":["activeSpeakerScoreDidChangeWithScores","open fun activeSpeakerScoreDidChangeWithScores(scores: Map<Any?, *>): <Error class: unknown class>","com.wannaverse.chimesdk.ActiveSpeakerObserverImpl.activeSpeakerScoreDidChangeWithScores"]},{"name":"open fun attendeesDidDropWithAttendeeInfo(attendeeInfo: List<*>): <Error class: unknown class>","description":"com.wannaverse.chimesdk.RealTimeObserverImpl.attendeesDidDropWithAttendeeInfo","location":"chime-sdk/com.wannaverse.chimesdk/[ios]-real-time-observer-impl/attendees-did-drop-with-attendee-info.html","searchKeys":["attendeesDidDropWithAttendeeInfo","open fun attendeesDidDropWithAttendeeInfo(attendeeInfo: List<*>): <Error class: unknown class>","com.wannaverse.chimesdk.RealTimeObserverImpl.attendeesDidDropWithAttendeeInfo"]},{"name":"open fun attendeesDidJoinWithAttendeeInfo(attendeeInfo: List<*>): <Error class: unknown class>","description":"com.wannaverse.chimesdk.RealTimeObserverImpl.attendeesDidJoinWithAttendeeInfo","location":"chime-sdk/com.wannaverse.chimesdk/[ios]-real-time-observer-impl/attendees-did-join-with-attendee-info.html","searchKeys":["attendeesDidJoinWithAttendeeInfo","open fun attendeesDidJoinWithAttendeeInfo(attendeeInfo: List<*>): <Error class: unknown class>","com.wannaverse.chimesdk.RealTimeObserverImpl.attendeesDidJoinWithAttendeeInfo"]},{"name":"open fun attendeesDidLeaveWithAttendeeInfo(attendeeInfo: List<*>): <Error class: unknown class>","description":"com.wannaverse.chimesdk.RealTimeObserverImpl.attendeesDidLeaveWithAttendeeInfo","location":"chime-sdk/com.wannaverse.chimesdk/[ios]-real-time-observer-impl/attendees-did-leave-with-attendee-info.html","searchKeys":["attendeesDidLeaveWithAttendeeInfo","open fun attendeesDidLeaveWithAttendeeInfo(attendeeInfo: List<*>): <Error class: unknown class>","com.wannaverse.chimesdk.RealTimeObserverImpl.attendeesDidLeaveWithAttendeeInfo"]},{"name":"open fun attendeesDidMuteWithAttendeeInfo(attendeeInfo: List<*>): <Error class: unknown class>","description":"com.wannaverse.chimesdk.RealTimeObserverImpl.attendeesDidMuteWithAttendeeInfo","location":"chime-sdk/com.wannaverse.chimesdk/[ios]-real-time-observer-impl/attendees-did-mute-with-attendee-info.html","searchKeys":["attendeesDidMuteWithAttendeeInfo","open fun attendeesDidMuteWithAttendeeInfo(attendeeInfo: List<*>): <Error class: unknown class>","com.wannaverse.chimesdk.RealTimeObserverImpl.attendeesDidMuteWithAttendeeInfo"]},{"name":"open fun attendeesDidUnmuteWithAttendeeInfo(attendeeInfo: List<*>): <Error class: unknown class>","description":"com.wannaverse.chimesdk.RealTimeObserverImpl.attendeesDidUnmuteWithAttendeeInfo","location":"chime-sdk/com.wannaverse.chimesdk/[ios]-real-time-observer-impl/attendees-did-unmute-with-attendee-info.html","searchKeys":["attendeesDidUnmuteWithAttendeeInfo","open fun attendeesDidUnmuteWithAttendeeInfo(attendeeInfo: List<*>): <Error class: unknown class>","com.wannaverse.chimesdk.RealTimeObserverImpl.attendeesDidUnmuteWithAttendeeInfo"]},{"name":"open fun audioDeviceDidChangeWithFreshAudioDeviceList(freshAudioDeviceList: List<*>)","description":"com.wannaverse.chimesdk.DeviceObserverImpl.audioDeviceDidChangeWithFreshAudioDeviceList","location":"chime-sdk/com.wannaverse.chimesdk/[ios]-device-observer-impl/audio-device-did-change-with-fresh-audio-device-list.html","searchKeys":["audioDeviceDidChangeWithFreshAudioDeviceList","open fun audioDeviceDidChangeWithFreshAudioDeviceList(freshAudioDeviceList: List<*>)","com.wannaverse.chimesdk.DeviceObserverImpl.audioDeviceDidChangeWithFreshAudioDeviceList"]},{"name":"open fun audioSessionDidCancelReconnect()","description":"com.wannaverse.chimesdk.AudioVideoObserverImpl.audioSessionDidCancelReconnect","location":"chime-sdk/com.wannaverse.chimesdk/[ios]-audio-video-observer-impl/audio-session-did-cancel-reconnect.html","searchKeys":["audioSessionDidCancelReconnect","open fun audioSessionDidCancelReconnect()","com.wannaverse.chimesdk.AudioVideoObserverImpl.audioSessionDidCancelReconnect"]},{"name":"open fun audioSessionDidDrop()","description":"com.wannaverse.chimesdk.AudioVideoObserverImpl.audioSessionDidDrop","location":"chime-sdk/com.wannaverse.chimesdk/[ios]-audio-video-observer-impl/audio-session-did-drop.html","searchKeys":["audioSessionDidDrop","open fun audioSessionDidDrop()","com.wannaverse.chimesdk.AudioVideoObserverImpl.audioSessionDidDrop"]},{"name":"open fun audioSessionDidStartConnectingWithReconnecting(reconnecting: Boolean)","description":"com.wannaverse.chimesdk.AudioVideoObserverImpl.audioSessionDidStartConnectingWithReconnecting","location":"chime-sdk/com.wannaverse.chimesdk/[ios]-audio-video-observer-impl/audio-session-did-start-connecting-with-reconnecting.html","searchKeys":["audioSessionDidStartConnectingWithReconnecting","open fun audioSessionDidStartConnectingWithReconnecting(reconnecting: Boolean)","com.wannaverse.chimesdk.AudioVideoObserverImpl.audioSessionDidStartConnectingWithReconnecting"]},{"name":"open fun audioSessionDidStartWithReconnecting(reconnecting: Boolean)","description":"com.wannaverse.chimesdk.AudioVideoObserverImpl.audioSessionDidStartWithReconnecting","location":"chime-sdk/com.wannaverse.chimesdk/[ios]-audio-video-observer-impl/audio-session-did-start-with-reconnecting.html","searchKeys":["audioSessionDidStartWithReconnecting","open fun audioSessionDidStartWithReconnecting(reconnecting: Boolean)","com.wannaverse.chimesdk.AudioVideoObserverImpl.audioSessionDidStartWithReconnecting"]},{"name":"open fun audioSessionDidStopWithStatusWithSessionStatus(sessionStatus: <Error class: unknown class>)","description":"com.wannaverse.chimesdk.AudioVideoObserverImpl.audioSessionDidStopWithStatusWithSessionStatus","location":"chime-sdk/com.wannaverse.chimesdk/[ios]-audio-video-observer-impl/audio-session-did-stop-with-status-with-session-status.html","searchKeys":["audioSessionDidStopWithStatusWithSessionStatus","open fun audioSessionDidStopWithStatusWithSessionStatus(sessionStatus: <Error class: unknown class>)","com.wannaverse.chimesdk.AudioVideoObserverImpl.audioSessionDidStopWithStatusWithSessionStatus"]},{"name":"open fun cameraSendAvailabilityDidChangeWithAvailable(available: Boolean)","description":"com.wannaverse.chimesdk.AudioVideoObserverImpl.cameraSendAvailabilityDidChangeWithAvailable","location":"chime-sdk/com.wannaverse.chimesdk/[ios]-audio-video-observer-impl/camera-send-availability-did-change-with-available.html","searchKeys":["cameraSendAvailabilityDidChangeWithAvailable","open fun cameraSendAvailabilityDidChangeWithAvailable(available: Boolean)","com.wannaverse.chimesdk.AudioVideoObserverImpl.cameraSendAvailabilityDidChangeWithAvailable"]},{"name":"open fun connectionDidBecomePoor()","description":"com.wannaverse.chimesdk.AudioVideoObserverImpl.connectionDidBecomePoor","location":"chime-sdk/com.wannaverse.chimesdk/[ios]-audio-video-observer-impl/connection-did-become-poor.html","searchKeys":["connectionDidBecomePoor","open fun connectionDidBecomePoor()","com.wannaverse.chimesdk.AudioVideoObserverImpl.connectionDidBecomePoor"]},{"name":"open fun connectionDidRecover()","description":"com.wannaverse.chimesdk.AudioVideoObserverImpl.connectionDidRecover","location":"chime-sdk/com.wannaverse.chimesdk/[ios]-audio-video-observer-impl/connection-did-recover.html","searchKeys":["connectionDidRecover","open fun connectionDidRecover()","com.wannaverse.chimesdk.AudioVideoObserverImpl.connectionDidRecover"]},{"name":"open fun dataMessageDidReceivedWithDataMessage(dataMessage: <Error class: unknown class>): <Error class: unknown class>","description":"com.wannaverse.chimesdk.DataMessageObserverImpl.dataMessageDidReceivedWithDataMessage","location":"chime-sdk/com.wannaverse.chimesdk/[ios]-data-message-observer-impl/data-message-did-received-with-data-message.html","searchKeys":["dataMessageDidReceivedWithDataMessage","open fun dataMessageDidReceivedWithDataMessage(dataMessage: <Error class: unknown class>): <Error class: unknown class>","com.wannaverse.chimesdk.DataMessageObserverImpl.dataMessageDidReceivedWithDataMessage"]},{"name":"open fun observerId(): String","description":"com.wannaverse.chimesdk.ActiveSpeakerObserverImpl.observerId","location":"chime-sdk/com.wannaverse.chimesdk/[ios]-active-speaker-observer-impl/observer-id.html","searchKeys":["observerId","open fun observerId(): String","com.wannaverse.chimesdk.ActiveSpeakerObserverImpl.observerId"]},{"name":"open fun remoteVideoSourcesDidBecomeAvailableWithSources(sources: List<*>)","description":"com.wannaverse.chimesdk.AudioVideoObserverImpl.remoteVideoSourcesDidBecomeAvailableWithSources","location":"chime-sdk/com.wannaverse.chimesdk/[ios]-audio-video-observer-impl/remote-video-sources-did-become-available-with-sources.html","searchKeys":["remoteVideoSourcesDidBecomeAvailableWithSources","open fun remoteVideoSourcesDidBecomeAvailableWithSources(sources: List<*>)","com.wannaverse.chimesdk.AudioVideoObserverImpl.remoteVideoSourcesDidBecomeAvailableWithSources"]},{"name":"open fun remoteVideoSourcesDidBecomeUnavailableWithSources(sources: List<*>)","description":"com.wannaverse.chimesdk.AudioVideoObserverImpl.remoteVideoSourcesDidBecomeUnavailableWithSources","location":"chime-sdk/com.wannaverse.chimesdk/[ios]-audio-video-observer-impl/remote-video-sources-did-become-unavailable-with-sources.html","searchKeys":["remoteVideoSourcesDidBecomeUnavailableWithSources","open fun remoteVideoSourcesDidBecomeUnavailableWithSources(sources: List<*>)","com.wannaverse.chimesdk.AudioVideoObserverImpl.remoteVideoSourcesDidBecomeUnavailableWithSources"]},{"name":"open fun scoresCallbackIntervalMs(): <Error class: unknown class>","description":"com.wannaverse.chimesdk.ActiveSpeakerObserverImpl.scoresCallbackIntervalMs","location":"chime-sdk/com.wannaverse.chimesdk/[ios]-active-speaker-observer-impl/scores-callback-interval-ms.html","searchKeys":["scoresCallbackIntervalMs","open fun scoresCallbackIntervalMs(): <Error class: unknown class>","com.wannaverse.chimesdk.ActiveSpeakerObserverImpl.scoresCallbackIntervalMs"]},{"name":"open fun signalStrengthDidChangeWithSignalUpdates(signalUpdates: List<*>): <Error class: unknown class>","description":"com.wannaverse.chimesdk.RealTimeObserverImpl.signalStrengthDidChangeWithSignalUpdates","location":"chime-sdk/com.wannaverse.chimesdk/[ios]-real-time-observer-impl/signal-strength-did-change-with-signal-updates.html","searchKeys":["signalStrengthDidChangeWithSignalUpdates","open fun signalStrengthDidChangeWithSignalUpdates(signalUpdates: List<*>): <Error class: unknown class>","com.wannaverse.chimesdk.RealTimeObserverImpl.signalStrengthDidChangeWithSignalUpdates"]},{"name":"open fun videoSessionDidStartConnecting()","description":"com.wannaverse.chimesdk.AudioVideoObserverImpl.videoSessionDidStartConnecting","location":"chime-sdk/com.wannaverse.chimesdk/[ios]-audio-video-observer-impl/video-session-did-start-connecting.html","searchKeys":["videoSessionDidStartConnecting","open fun videoSessionDidStartConnecting()","com.wannaverse.chimesdk.AudioVideoObserverImpl.videoSessionDidStartConnecting"]},{"name":"open fun videoSessionDidStartWithStatusWithSessionStatus(sessionStatus: <Error class: unknown class>)","description":"com.wannaverse.chimesdk.AudioVideoObserverImpl.videoSessionDidStartWithStatusWithSessionStatus","location":"chime-sdk/com.wannaverse.chimesdk/[ios]-audio-video-observer-impl/video-session-did-start-with-status-with-session-status.html","searchKeys":["videoSessionDidStartWithStatusWithSessionStatus","open fun videoSessionDidStartWithStatusWithSessionStatus(sessionStatus: <Error class: unknown class>)","com.wannaverse.chimesdk.AudioVideoObserverImpl.videoSessionDidStartWithStatusWithSessionStatus"]},{"name":"open fun videoSessionDidStopWithStatusWithSessionStatus(sessionStatus: <Error class: unknown class>)","description":"com.wannaverse.chimesdk.AudioVideoObserverImpl.videoSessionDidStopWithStatusWithSessionStatus","location":"chime-sdk/com.wannaverse.chimesdk/[ios]-audio-video-observer-impl/video-session-did-stop-with-status-with-session-status.html","searchKeys":["videoSessionDidStopWithStatusWithSessionStatus","open fun videoSessionDidStopWithStatusWithSessionStatus(sessionStatus: <Error class: unknown class>)","com.wannaverse.chimesdk.AudioVideoObserverImpl.videoSessionDidStopWithStatusWithSessionStatus"]},{"name":"open fun videoTileDidAddWithTileState(tileState: <Error class: unknown class>)","description":"com.wannaverse.chimesdk.VideoTileObserverImpl.videoTileDidAddWithTileState","location":"chime-sdk/com.wannaverse.chimesdk/[ios]-video-tile-observer-impl/video-tile-did-add-with-tile-state.html","searchKeys":["videoTileDidAddWithTileState","open fun videoTileDidAddWithTileState(tileState: <Error class: unknown class>)","com.wannaverse.chimesdk.VideoTileObserverImpl.videoTileDidAddWithTileState"]},{"name":"open fun videoTileDidPauseWithTileState(tileState: <Error class: unknown class>)","description":"com.wannaverse.chimesdk.VideoTileObserverImpl.videoTileDidPauseWithTileState","location":"chime-sdk/com.wannaverse.chimesdk/[ios]-video-tile-observer-impl/video-tile-did-pause-with-tile-state.html","searchKeys":["videoTileDidPauseWithTileState","open fun videoTileDidPauseWithTileState(tileState: <Error class: unknown class>)","com.wannaverse.chimesdk.VideoTileObserverImpl.videoTileDidPauseWithTileState"]},{"name":"open fun videoTileDidRemoveWithTileState(tileState: <Error class: unknown class>)","description":"com.wannaverse.chimesdk.VideoTileObserverImpl.videoTileDidRemoveWithTileState","location":"chime-sdk/com.wannaverse.chimesdk/[ios]-video-tile-observer-impl/video-tile-did-remove-with-tile-state.html","searchKeys":["videoTileDidRemoveWithTileState","open fun videoTileDidRemoveWithTileState(tileState: <Error class: unknown class>)","com.wannaverse.chimesdk.VideoTileObserverImpl.videoTileDidRemoveWithTileState"]},{"name":"open fun videoTileDidResumeWithTileState(tileState: <Error class: unknown class>)","description":"com.wannaverse.chimesdk.VideoTileObserverImpl.videoTileDidResumeWithTileState","location":"chime-sdk/com.wannaverse.chimesdk/[ios]-video-tile-observer-impl/video-tile-did-resume-with-tile-state.html","searchKeys":["videoTileDidResumeWithTileState","open fun videoTileDidResumeWithTileState(tileState: <Error class: unknown class>)","com.wannaverse.chimesdk.VideoTileObserverImpl.videoTileDidResumeWithTileState"]},{"name":"open fun videoTileSizeDidChangeWithTileState(tileState: <Error class: unknown class>)","description":"com.wannaverse.chimesdk.VideoTileObserverImpl.videoTileSizeDidChangeWithTileState","location":"chime-sdk/com.wannaverse.chimesdk/[ios]-video-tile-observer-impl/video-tile-size-did-change-with-tile-state.html","searchKeys":["videoTileSizeDidChangeWithTileState","open fun videoTileSizeDidChangeWithTileState(tileState: <Error class: unknown class>)","com.wannaverse.chimesdk.VideoTileObserverImpl.videoTileSizeDidChangeWithTileState"]},{"name":"open fun volumeDidChangeWithVolumeUpdates(volumeUpdates: List<*>): <Error class: unknown class>","description":"com.wannaverse.chimesdk.RealTimeObserverImpl.volumeDidChangeWithVolumeUpdates","location":"chime-sdk/com.wannaverse.chimesdk/[ios]-real-time-observer-impl/volume-did-change-with-volume-updates.html","searchKeys":["volumeDidChangeWithVolumeUpdates","open fun volumeDidChangeWithVolumeUpdates(volumeUpdates: List<*>): <Error class: unknown class>","com.wannaverse.chimesdk.RealTimeObserverImpl.volumeDidChangeWithVolumeUpdates"]},{"name":"open override fun onActiveSpeakerDetected(attendeeInfo: Array<AttendeeInfo>)","description":"com.wannaverse.chimesdk.ActiveSpeakerObserverImpl.onActiveSpeakerDetected","location":"chime-sdk/com.wannaverse.chimesdk/[android]-active-speaker-observer-impl/on-active-speaker-detected.html","searchKeys":["onActiveSpeakerDetected","open override fun onActiveSpeakerDetected(attendeeInfo: Array<AttendeeInfo>)","com.wannaverse.chimesdk.ActiveSpeakerObserverImpl.onActiveSpeakerDetected"]},{"name":"open override fun onActiveSpeakerScoreChanged(scores: Map<AttendeeInfo, Double>): <Error class: unknown class>","description":"com.wannaverse.chimesdk.ActiveSpeakerObserverImpl.onActiveSpeakerScoreChanged","location":"chime-sdk/com.wannaverse.chimesdk/[android]-active-speaker-observer-impl/on-active-speaker-score-changed.html","searchKeys":["onActiveSpeakerScoreChanged","open override fun onActiveSpeakerScoreChanged(scores: Map<AttendeeInfo, Double>): <Error class: unknown class>","com.wannaverse.chimesdk.ActiveSpeakerObserverImpl.onActiveSpeakerScoreChanged"]},{"name":"open override fun onAttendeesDropped(attendeeInfo: Array<AttendeeInfo>)","description":"com.wannaverse.chimesdk.RealTimeObserverImpl.onAttendeesDropped","location":"chime-sdk/com.wannaverse.chimesdk/[android]-real-time-observer-impl/on-attendees-dropped.html","searchKeys":["onAttendeesDropped","open override fun onAttendeesDropped(attendeeInfo: Array<AttendeeInfo>)","com.wannaverse.chimesdk.RealTimeObserverImpl.onAttendeesDropped"]},{"name":"open override fun onAttendeesJoined(attendeeInfo: Array<AttendeeInfo>)","description":"com.wannaverse.chimesdk.RealTimeObserverImpl.onAttendeesJoined","location":"chime-sdk/com.wannaverse.chimesdk/[android]-real-time-observer-impl/on-attendees-joined.html","searchKeys":["onAttendeesJoined","open override fun onAttendeesJoined(attendeeInfo: Array<AttendeeInfo>)","com.wannaverse.chimesdk.RealTimeObserverImpl.onAttendeesJoined"]},{"name":"open override fun onAttendeesLeft(attendeeInfo: Array<AttendeeInfo>)","description":"com.wannaverse.chimesdk.RealTimeObserverImpl.onAttendeesLeft","location":"chime-sdk/com.wannaverse.chimesdk/[android]-real-time-observer-impl/on-attendees-left.html","searchKeys":["onAttendeesLeft","open override fun onAttendeesLeft(attendeeInfo: Array<AttendeeInfo>)","com.wannaverse.chimesdk.RealTimeObserverImpl.onAttendeesLeft"]},{"name":"open override fun onAttendeesMuted(attendeeInfo: Array<AttendeeInfo>)","description":"com.wannaverse.chimesdk.RealTimeObserverImpl.onAttendeesMuted","location":"chime-sdk/com.wannaverse.chimesdk/[android]-real-time-observer-impl/on-attendees-muted.html","searchKeys":["onAttendeesMuted","open override fun onAttendeesMuted(attendeeInfo: Array<AttendeeInfo>)","com.wannaverse.chimesdk.RealTimeObserverImpl.onAttendeesMuted"]},{"name":"open override fun onAttendeesUnmuted(attendeeInfo: Array<AttendeeInfo>)","description":"com.wannaverse.chimesdk.RealTimeObserverImpl.onAttendeesUnmuted","location":"chime-sdk/com.wannaverse.chimesdk/[android]-real-time-observer-impl/on-attendees-unmuted.html","searchKeys":["onAttendeesUnmuted","open override fun onAttendeesUnmuted(attendeeInfo: Array<AttendeeInfo>)","com.wannaverse.chimesdk.RealTimeObserverImpl.onAttendeesUnmuted"]},{"name":"open override fun onAudioDeviceChanged(freshAudioDeviceList: List<MediaDevice>)","description":"com.wannaverse.chimesdk.DeviceObserverImpl.onAudioDeviceChanged","location":"chime-sdk/com.wannaverse.chimesdk/[android]-device-observer-impl/on-audio-device-changed.html","searchKeys":["onAudioDeviceChanged","open override fun onAudioDeviceChanged(freshAudioDeviceList: List<MediaDevice>)","com.wannaverse.chimesdk.DeviceObserverImpl.onAudioDeviceChanged"]},{"name":"open override fun onAudioSessionCancelledReconnect()","description":"com.wannaverse.chimesdk.AudioVideoObserverImpl.onAudioSessionCancelledReconnect","location":"chime-sdk/com.wannaverse.chimesdk/[android]-audio-video-observer-impl/on-audio-session-cancelled-reconnect.html","searchKeys":["onAudioSessionCancelledReconnect","open override fun onAudioSessionCancelledReconnect()","com.wannaverse.chimesdk.AudioVideoObserverImpl.onAudioSessionCancelledReconnect"]},{"name":"open override fun onAudioSessionDropped()","description":"com.wannaverse.chimesdk.AudioVideoObserverImpl.onAudioSessionDropped","location":"chime-sdk/com.wannaverse.chimesdk/[android]-audio-video-observer-impl/on-audio-session-dropped.html","searchKeys":["onAudioSessionDropped","open override fun onAudioSessionDropped()","com.wannaverse.chimesdk.AudioVideoObserverImpl.onAudioSessionDropped"]},{"name":"open override fun onAudioSessionStarted(reconnecting: Boolean)","description":"com.wannaverse.chimesdk.AudioVideoObserverImpl.onAudioSessionStarted","location":"chime-sdk/com.wannaverse.chimesdk/[android]-audio-video-observer-impl/on-audio-session-started.html","searchKeys":["onAudioSessionStarted","open override fun onAudioSessionStarted(reconnecting: Boolean)","com.wannaverse.chimesdk.AudioVideoObserverImpl.onAudioSessionStarted"]},{"name":"open override fun onAudioSessionStartedConnecting(reconnecting: Boolean)","description":"com.wannaverse.chimesdk.AudioVideoObserverImpl.onAudioSessionStartedConnecting","location":"chime-sdk/com.wannaverse.chimesdk/[android]-audio-video-observer-impl/on-audio-session-started-connecting.html","searchKeys":["onAudioSessionStartedConnecting","open override fun onAudioSessionStartedConnecting(reconnecting: Boolean)","com.wannaverse.chimesdk.AudioVideoObserverImpl.onAudioSessionStartedConnecting"]},{"name":"open override fun onAudioSessionStopped(sessionStatus: MeetingSessionStatus)","description":"com.wannaverse.chimesdk.AudioVideoObserverImpl.onAudioSessionStopped","location":"chime-sdk/com.wannaverse.chimesdk/[android]-audio-video-observer-impl/on-audio-session-stopped.html","searchKeys":["onAudioSessionStopped","open override fun onAudioSessionStopped(sessionStatus: MeetingSessionStatus)","com.wannaverse.chimesdk.AudioVideoObserverImpl.onAudioSessionStopped"]},{"name":"open override fun onCameraSendAvailabilityUpdated(available: Boolean)","description":"com.wannaverse.chimesdk.AudioVideoObserverImpl.onCameraSendAvailabilityUpdated","location":"chime-sdk/com.wannaverse.chimesdk/[android]-audio-video-observer-impl/on-camera-send-availability-updated.html","searchKeys":["onCameraSendAvailabilityUpdated","open override fun onCameraSendAvailabilityUpdated(available: Boolean)","com.wannaverse.chimesdk.AudioVideoObserverImpl.onCameraSendAvailabilityUpdated"]},{"name":"open override fun onConnectionBecamePoor()","description":"com.wannaverse.chimesdk.AudioVideoObserverImpl.onConnectionBecamePoor","location":"chime-sdk/com.wannaverse.chimesdk/[android]-audio-video-observer-impl/on-connection-became-poor.html","searchKeys":["onConnectionBecamePoor","open override fun onConnectionBecamePoor()","com.wannaverse.chimesdk.AudioVideoObserverImpl.onConnectionBecamePoor"]},{"name":"open override fun onConnectionRecovered()","description":"com.wannaverse.chimesdk.AudioVideoObserverImpl.onConnectionRecovered","location":"chime-sdk/com.wannaverse.chimesdk/[android]-audio-video-observer-impl/on-connection-recovered.html","searchKeys":["onConnectionRecovered","open override fun onConnectionRecovered()","com.wannaverse.chimesdk.AudioVideoObserverImpl.onConnectionRecovered"]},{"name":"open override fun onDataMessageReceived(dataMessage: DataMessage): <Error class: unknown class>","description":"com.wannaverse.chimesdk.DataMessageObserverImpl.onDataMessageReceived","location":"chime-sdk/com.wannaverse.chimesdk/[android]-data-message-observer-impl/on-data-message-received.html","searchKeys":["onDataMessageReceived","open override fun onDataMessageReceived(dataMessage: DataMessage): <Error class: unknown class>","com.wannaverse.chimesdk.DataMessageObserverImpl.onDataMessageReceived"]},{"name":"open override fun onRemoteVideoSourceAvailable(sources: List<RemoteVideoSource>)","description":"com.wannaverse.chimesdk.AudioVideoObserverImpl.onRemoteVideoSourceAvailable","location":"chime-sdk/com.wannaverse.chimesdk/[android]-audio-video-observer-impl/on-remote-video-source-available.html","searchKeys":["onRemoteVideoSourceAvailable","open override fun onRemoteVideoSourceAvailable(sources: List<RemoteVideoSource>)","com.wannaverse.chimesdk.AudioVideoObserverImpl.onRemoteVideoSourceAvailable"]},{"name":"open override fun onRemoteVideoSourceUnavailable(sources: List<RemoteVideoSource>)","description":"com.wannaverse.chimesdk.AudioVideoObserverImpl.onRemoteVideoSourceUnavailable","location":"chime-sdk/com.wannaverse.chimesdk/[android]-audio-video-observer-impl/on-remote-video-source-unavailable.html","searchKeys":["onRemoteVideoSourceUnavailable","open override fun onRemoteVideoSourceUnavailable(sources: List<RemoteVideoSource>)","com.wannaverse.chimesdk.AudioVideoObserverImpl.onRemoteVideoSourceUnavailable"]},{"name":"open override fun onSignalStrengthChanged(signalUpdates: Array<SignalUpdate>): <Error class: unknown class>","description":"com.wannaverse.chimesdk.RealTimeObserverImpl.onSignalStrengthChanged","location":"chime-sdk/com.wannaverse.chimesdk/[android]-real-time-observer-impl/on-signal-strength-changed.html","searchKeys":["onSignalStrengthChanged","open override fun onSignalStrengthChanged(signalUpdates: Array<SignalUpdate>): <Error class: unknown class>","com.wannaverse.chimesdk.RealTimeObserverImpl.onSignalStrengthChanged"]},{"name":"open override fun onVideoSessionStarted(sessionStatus: MeetingSessionStatus)","description":"com.wannaverse.chimesdk.AudioVideoObserverImpl.onVideoSessionStarted","location":"chime-sdk/com.wannaverse.chimesdk/[android]-audio-video-observer-impl/on-video-session-started.html","searchKeys":["onVideoSessionStarted","open override fun onVideoSessionStarted(sessionStatus: MeetingSessionStatus)","com.wannaverse.chimesdk.AudioVideoObserverImpl.onVideoSessionStarted"]},{"name":"open override fun onVideoSessionStartedConnecting()","description":"com.wannaverse.chimesdk.AudioVideoObserverImpl.onVideoSessionStartedConnecting","location":"chime-sdk/com.wannaverse.chimesdk/[android]-audio-video-observer-impl/on-video-session-started-connecting.html","searchKeys":["onVideoSessionStartedConnecting","open override fun onVideoSessionStartedConnecting()","com.wannaverse.chimesdk.AudioVideoObserverImpl.onVideoSessionStartedConnecting"]},{"name":"open override fun onVideoSessionStopped(sessionStatus: MeetingSessionStatus)","description":"com.wannaverse.chimesdk.AudioVideoObserverImpl.onVideoSessionStopped","location":"chime-sdk/com.wannaverse.chimesdk/[android]-audio-video-observer-impl/on-video-session-stopped.html","searchKeys":["onVideoSessionStopped","open override fun onVideoSessionStopped(sessionStatus: MeetingSessionStatus)","com.wannaverse.chimesdk.AudioVideoObserverImpl.onVideoSessionStopped"]},{"name":"open override fun onVideoTileAdded(tileState: VideoTileState)","description":"com.wannaverse.chimesdk.VideoTileObserverImpl.onVideoTileAdded","location":"chime-sdk/com.wannaverse.chimesdk/[android]-video-tile-observer-impl/on-video-tile-added.html","searchKeys":["onVideoTileAdded","open override fun onVideoTileAdded(tileState: VideoTileState)","com.wannaverse.chimesdk.VideoTileObserverImpl.onVideoTileAdded"]},{"name":"open override fun onVideoTilePaused(tileState: VideoTileState)","description":"com.wannaverse.chimesdk.VideoTileObserverImpl.onVideoTilePaused","location":"chime-sdk/com.wannaverse.chimesdk/[android]-video-tile-observer-impl/on-video-tile-paused.html","searchKeys":["onVideoTilePaused","open override fun onVideoTilePaused(tileState: VideoTileState)","com.wannaverse.chimesdk.VideoTileObserverImpl.onVideoTilePaused"]},{"name":"open override fun onVideoTileRemoved(tileState: VideoTileState)","description":"com.wannaverse.chimesdk.VideoTileObserverImpl.onVideoTileRemoved","location":"chime-sdk/com.wannaverse.chimesdk/[android]-video-tile-observer-impl/on-video-tile-removed.html","searchKeys":["onVideoTileRemoved","open override fun onVideoTileRemoved(tileState: VideoTileState)","com.wannaverse.chimesdk.VideoTileObserverImpl.onVideoTileRemoved"]},{"name":"open override fun onVideoTileResumed(tileState: VideoTileState)","description":"com.wannaverse.chimesdk.VideoTileObserverImpl.onVideoTileResumed","location":"chime-sdk/com.wannaverse.chimesdk/[android]-video-tile-observer-impl/on-video-tile-resumed.html","searchKeys":["onVideoTileResumed","open override fun onVideoTileResumed(tileState: VideoTileState)","com.wannaverse.chimesdk.VideoTileObserverImpl.onVideoTileResumed"]},{"name":"open override fun onVideoTileSizeChanged(tileState: VideoTileState)","description":"com.wannaverse.chimesdk.VideoTileObserverImpl.onVideoTileSizeChanged","location":"chime-sdk/com.wannaverse.chimesdk/[android]-video-tile-observer-impl/on-video-tile-size-changed.html","searchKeys":["onVideoTileSizeChanged","open override fun onVideoTileSizeChanged(tileState: VideoTileState)","com.wannaverse.chimesdk.VideoTileObserverImpl.onVideoTileSizeChanged"]},{"name":"open override fun onVolumeChanged(volumeUpdates: Array<VolumeUpdate>): <Error class: unknown class>","description":"com.wannaverse.chimesdk.RealTimeObserverImpl.onVolumeChanged","location":"chime-sdk/com.wannaverse.chimesdk/[android]-real-time-observer-impl/on-volume-changed.html","searchKeys":["onVolumeChanged","open override fun onVolumeChanged(volumeUpdates: Array<VolumeUpdate>): <Error class: unknown class>","com.wannaverse.chimesdk.RealTimeObserverImpl.onVolumeChanged"]},{"name":"open override val scoreCallbackIntervalMs: Int = 500","description":"com.wannaverse.chimesdk.ActiveSpeakerObserverImpl.scoreCallbackIntervalMs","location":"chime-sdk/com.wannaverse.chimesdk/[android]-active-speaker-observer-impl/score-callback-interval-ms.html","searchKeys":["scoreCallbackIntervalMs","open override val scoreCallbackIntervalMs: Int = 500","com.wannaverse.chimesdk.ActiveSpeakerObserverImpl.scoreCallbackIntervalMs"]},{"name":"val attendeeId: String","description":"com.wannaverse.chimesdk.Attendee.attendeeId","location":"chime-sdk/com.wannaverse.chimesdk/-attendee/attendee-id.html","searchKeys":["attendeeId","val attendeeId: String","com.wannaverse.chimesdk.Attendee.attendeeId"]},{"name":"val attendeeId: String","description":"com.wannaverse.chimesdk.MeetingInformation.attendeeId","location":"chime-sdk/com.wannaverse.chimesdk/-meeting-information/attendee-id.html","searchKeys":["attendeeId","val attendeeId: String","com.wannaverse.chimesdk.MeetingInformation.attendeeId"]},{"name":"val audioFallbackURL: String","description":"com.wannaverse.chimesdk.MeetingInformation.audioFallbackURL","location":"chime-sdk/com.wannaverse.chimesdk/-meeting-information/audio-fallback-u-r-l.html","searchKeys":["audioFallbackURL","val audioFallbackURL: String","com.wannaverse.chimesdk.MeetingInformation.audioFallbackURL"]},{"name":"val audioHostURL: String","description":"com.wannaverse.chimesdk.MeetingInformation.audioHostURL","location":"chime-sdk/com.wannaverse.chimesdk/-meeting-information/audio-host-u-r-l.html","searchKeys":["audioHostURL","val audioHostURL: String","com.wannaverse.chimesdk.MeetingInformation.audioHostURL"]},{"name":"val content: String","description":"com.wannaverse.chimesdk.ChimeMessage.content","location":"chime-sdk/com.wannaverse.chimesdk/-chime-message/content.html","searchKeys":["content","val content: String","com.wannaverse.chimesdk.ChimeMessage.content"]},{"name":"val content: String","description":"com.wannaverse.chimesdk.TextMessage.content","location":"chime-sdk/com.wannaverse.chimesdk/-text-message/content.html","searchKeys":["content","val content: String","com.wannaverse.chimesdk.TextMessage.content"]},{"name":"val externalMeetingId: String","description":"com.wannaverse.chimesdk.MeetingInformation.externalMeetingId","location":"chime-sdk/com.wannaverse.chimesdk/-meeting-information/external-meeting-id.html","searchKeys":["externalMeetingId","val externalMeetingId: String","com.wannaverse.chimesdk.MeetingInformation.externalMeetingId"]},{"name":"val externalUserId: String","description":"com.wannaverse.chimesdk.Attendee.externalUserId","location":"chime-sdk/com.wannaverse.chimesdk/-attendee/external-user-id.html","searchKeys":["externalUserId","val externalUserId: String","com.wannaverse.chimesdk.Attendee.externalUserId"]},{"name":"val externalUserId: String","description":"com.wannaverse.chimesdk.MeetingInformation.externalUserId","location":"chime-sdk/com.wannaverse.chimesdk/-meeting-information/external-user-id.html","searchKeys":["externalUserId","val externalUserId: String","com.wannaverse.chimesdk.MeetingInformation.externalUserId"]},{"name":"val ingestionURL: String","description":"com.wannaverse.chimesdk.MeetingInformation.ingestionURL","location":"chime-sdk/com.wannaverse.chimesdk/-meeting-information/ingestion-u-r-l.html","searchKeys":["ingestionURL","val ingestionURL: String","com.wannaverse.chimesdk.MeetingInformation.ingestionURL"]},{"name":"val joinToken: String","description":"com.wannaverse.chimesdk.MeetingInformation.joinToken","location":"chime-sdk/com.wannaverse.chimesdk/-meeting-information/join-token.html","searchKeys":["joinToken","val joinToken: String","com.wannaverse.chimesdk.MeetingInformation.joinToken"]},{"name":"val label: String","description":"com.wannaverse.chimesdk.AudioDevice.label","location":"chime-sdk/com.wannaverse.chimesdk/-audio-device/label.html","searchKeys":["label","val label: String","com.wannaverse.chimesdk.AudioDevice.label"]},{"name":"val listener: <Error class: unknown class>","description":"com.wannaverse.chimesdk.RealTimeObserverImpl.listener","location":"chime-sdk/com.wannaverse.chimesdk/[ios]-real-time-observer-impl/listener.html","searchKeys":["listener","val listener: <Error class: unknown class>","com.wannaverse.chimesdk.RealTimeObserverImpl.listener"]},{"name":"val listener: RealTimeEventListener","description":"com.wannaverse.chimesdk.RealTimeObserverImpl.listener","location":"chime-sdk/com.wannaverse.chimesdk/[android]-real-time-observer-impl/listener.html","searchKeys":["listener","val listener: RealTimeEventListener","com.wannaverse.chimesdk.RealTimeObserverImpl.listener"]},{"name":"val listeners: <Error class: unknown class>","description":"com.wannaverse.chimesdk.DataMessageObserverImpl.listeners","location":"chime-sdk/com.wannaverse.chimesdk/[android]-data-message-observer-impl/listeners.html","searchKeys":["listeners","val listeners: <Error class: unknown class>","com.wannaverse.chimesdk.DataMessageObserverImpl.listeners"]},{"name":"val listeners: <Error class: unknown class>","description":"com.wannaverse.chimesdk.DataMessageObserverImpl.listeners","location":"chime-sdk/com.wannaverse.chimesdk/[ios]-data-message-observer-impl/listeners.html","searchKeys":["listeners","val listeners: <Error class: unknown class>","com.wannaverse.chimesdk.DataMessageObserverImpl.listeners"]},{"name":"val localRenderView: <Error class: unknown class>","description":"com.wannaverse.chimesdk.VideoTileObserverImpl.localRenderView","location":"chime-sdk/com.wannaverse.chimesdk/[ios]-video-tile-observer-impl/local-render-view.html","searchKeys":["localRenderView","val localRenderView: <Error class: unknown class>","com.wannaverse.chimesdk.VideoTileObserverImpl.localRenderView"]},{"name":"val meetingId: String","description":"com.wannaverse.chimesdk.MeetingInformation.meetingId","location":"chime-sdk/com.wannaverse.chimesdk/-meeting-information/meeting-id.html","searchKeys":["meetingId","val meetingId: String","com.wannaverse.chimesdk.MeetingInformation.meetingId"]},{"name":"val onActiveSpeakersChanged: (Set<String>) -> Unit","description":"com.wannaverse.chimesdk.ActiveSpeakerObserverImpl.onActiveSpeakersChanged","location":"chime-sdk/com.wannaverse.chimesdk/[android]-active-speaker-observer-impl/on-active-speakers-changed.html","searchKeys":["onActiveSpeakersChanged","val onActiveSpeakersChanged: (Set<String>) -> Unit","com.wannaverse.chimesdk.ActiveSpeakerObserverImpl.onActiveSpeakersChanged"]},{"name":"val onActiveSpeakersChanged: (Set<String>) -> Unit","description":"com.wannaverse.chimesdk.ActiveSpeakerObserverImpl.onActiveSpeakersChanged","location":"chime-sdk/com.wannaverse.chimesdk/[ios]-active-speaker-observer-impl/on-active-speakers-changed.html","searchKeys":["onActiveSpeakersChanged","val onActiveSpeakersChanged: (Set<String>) -> Unit","com.wannaverse.chimesdk.ActiveSpeakerObserverImpl.onActiveSpeakersChanged"]},{"name":"val senderId: String","description":"com.wannaverse.chimesdk.ChimeMessage.senderId","location":"chime-sdk/com.wannaverse.chimesdk/-chime-message/sender-id.html","searchKeys":["senderId","val senderId: String","com.wannaverse.chimesdk.ChimeMessage.senderId"]},{"name":"val senderId: String","description":"com.wannaverse.chimesdk.TextMessage.senderId","location":"chime-sdk/com.wannaverse.chimesdk/-text-message/sender-id.html","searchKeys":["senderId","val senderId: String","com.wannaverse.chimesdk.TextMessage.senderId"]},{"name":"val signalingURL: String","description":"com.wannaverse.chimesdk.MeetingInformation.signalingURL","location":"chime-sdk/com.wannaverse.chimesdk/-meeting-information/signaling-u-r-l.html","searchKeys":["signalingURL","val signalingURL: String","com.wannaverse.chimesdk.MeetingInformation.signalingURL"]},{"name":"val timestamp: Long","description":"com.wannaverse.chimesdk.ChimeMessage.timestamp","location":"chime-sdk/com.wannaverse.chimesdk/-chime-message/timestamp.html","searchKeys":["timestamp","val timestamp: Long","com.wannaverse.chimesdk.ChimeMessage.timestamp"]},{"name":"val timestamp: Long","description":"com.wannaverse.chimesdk.TextMessage.timestamp","location":"chime-sdk/com.wannaverse.chimesdk/-text-message/timestamp.html","searchKeys":["timestamp","val timestamp: Long","com.wannaverse.chimesdk.TextMessage.timestamp"]},{"name":"val topic: String","description":"com.wannaverse.chimesdk.TextMessage.topic","location":"chime-sdk/com.wannaverse.chimesdk/-text-message/topic.html","searchKeys":["topic","val topic: String","com.wannaverse.chimesdk.TextMessage.topic"]},{"name":"val turnControlURL: String","description":"com.wannaverse.chimesdk.MeetingInformation.turnControlURL","location":"chime-sdk/com.wannaverse.chimesdk/-meeting-information/turn-control-u-r-l.html","searchKeys":["turnControlURL","val turnControlURL: String","com.wannaverse.chimesdk.MeetingInformation.turnControlURL"]},{"name":"val type: AudioDeviceType","description":"com.wannaverse.chimesdk.AudioDevice.type","location":"chime-sdk/com.wannaverse.chimesdk/-audio-device/type.html","searchKeys":["type","val type: AudioDeviceType","com.wannaverse.chimesdk.AudioDevice.type"]},{"name":"var localTileId: Int?","description":"com.wannaverse.chimesdk.VideoTileObserverImpl.localTileId","location":"chime-sdk/com.wannaverse.chimesdk/[android]-video-tile-observer-impl/local-tile-id.html","searchKeys":["localTileId","var localTileId: Int?","com.wannaverse.chimesdk.VideoTileObserverImpl.localTileId"]},{"name":"var localTileId: Long?","description":"com.wannaverse.chimesdk.VideoTileObserverImpl.localTileId","location":"chime-sdk/com.wannaverse.chimesdk/[ios]-video-tile-observer-impl/local-tile-id.html","searchKeys":["localTileId","var localTileId: Long?","com.wannaverse.chimesdk.VideoTileObserverImpl.localTileId"]}]